{
    "area": {
        "bbox": [
            [
                34.64675,
                135.34508
            ],
            [
                34.59518,
                135.49070
            ]
        ],
        "overpass": "relation[\"name\"=\"住之江区\"][admin_level=8]"
    },
    "target": {
        "park": {
            "overpass": [
                "relation[\"leisure\"=\"park\"]",
                "relation[\"leisure\"=\"playground\"]",
                "way[\"leisure\"=\"playground\"]",
                "way[\"leisure\"=\"park\"]"
            ],
            "tags": [
                "leisure=park",
                "leisure=playground"
            ],
            "views": [
                "name",
                "operator"
            ]
        },
        "garden": {
            "overpass": [
                "way[\"leisure\"=\"garden\"]",
                "way[\"landuse\"=\"grass\"]",
                "way[\"natural\"=\"scrub\"]",
                "way[\"landuse\"=\"farmland\"]",
                "way[\"landuse\"=\"allotments\"]"
            ],
            "tags": [
                "leisure=garden",
                "landuse=grass",
                "natural=scrub",
                "landuse=farmland",
                "landuse=allotments"
            ],
            "views": [
                "name",
                "operator"
            ]
        },
        "wikipedia": {
            "marker": "wikipedia.svg",
            "api": "wikipedia.org/w/api.php?format=json&action=query&prop=extracts&exintro=&explaintext=&titles=",
            "domain": "wikipedia.org",
            "tag": "wikipedia",
            "overpass": [
                "node[\"wikipedia\"][\"public_transport\"!=\"stop_position\"]",
                "way[\"wikipedia\"][!\"highway\"][!\"railway\"]",
                "relation[\"wikipedia\"][!\"route\"][!\"highway\"][!\"railway\"][\"name:ja\"!=\"本州\"]"
            ],
            "tags": [
                "wikipedia"
            ]
        }
    }
}